spin_rest_utils/__init__.py
spin_rest_utils/utils.py
spin_rest_utils-0.0.1.dist-info/LICENSE
spin_rest_utils-0.0.1.dist-info/METADATA
spin_rest_utils-0.0.1.dist-info/WHEEL
spin_rest_utils-0.0.1.dist-info/top_level.txt
spin_rest_utils-0.0.1.dist-info/RECORD
