Metadata-Version: 2.1
Name: spin-rest-utils
Version: 0.0.1
Summary: SPIn REST API utils for Ubersystem
Author: Victoria Earl
License-File: LICENSE
